easy_text_augmenter/__init__.py
easy_text_augmenter/augment.py
easy_text_augmenter/error_handling.py
easy_text_augmenter/info.py
easy_text_augmenter/test_iseng.py
easy_nlp_augmentation-1.4.dist-info/LICENSE
easy_nlp_augmentation-1.4.dist-info/METADATA
easy_nlp_augmentation-1.4.dist-info/WHEEL
easy_nlp_augmentation-1.4.dist-info/entry_points.txt
easy_nlp_augmentation-1.4.dist-info/top_level.txt
easy_nlp_augmentation-1.4.dist-info/RECORD
