Metadata-Version: 2.1
Name: easy-nlp-augmentation
Version: 1.4
Summary: A package for augmenting text data using NLP techniques directly in your pandas dataframe.
Home-page: https://github.com/Shizu-ka/easy-nlp-augmentation
Author: Shizuka
Author-email: shizuka0@proton.me
Classifier: Programming Language :: Python :: 3
Classifier: License :: OSI Approved :: MIT License
Classifier: Operating System :: OS Independent
Requires-Python: >=3.6
License-File: LICENSE
Requires-Dist: numpy
Requires-Dist: requests
Requires-Dist: pandas
Requires-Dist: nlpaug
